your_module/__init__.py
your_module/generator.py
serial_generator-0.1.0.dist-info/LICENSE
serial_generator-0.1.0.dist-info/METADATA
serial_generator-0.1.0.dist-info/WHEEL
serial_generator-0.1.0.dist-info/top_level.txt
serial_generator-0.1.0.dist-info/RECORD
