Metadata-Version: 2.1
Name: serial-generator
Version: 0.1.0
Summary: A simple module to generate random serial numbers.
Author: Your Name
Author-email: your_email@example.com
License: MIT
Classifier: Programming Language :: Python :: 3
Classifier: License :: OSI Approved :: MIT License
Classifier: Operating System :: OS Independent
Requires-Python: >=3.6
License-File: LICENSE
